sphinx_bib_domain/__init__.py
sphinx_bib_domain/_interface.py
sphinx_bib_domain/bib_domain.py
sphinx_bib_domain/parser.py
sphinx_bib_domain/py.typed
sphinx_bib_domain/_templates/bib_domain/entry.html.jinja
sphinx_bib_domain/_templates/bib_domain/entry.rst.jinja
sphinx_bib_domain/_templates/bib_domain/footer.rst.jinja
sphinx_bib_domain/_templates/bib_domain/header.rst.jinja
sphinx_bib_domain/_templates/bib_domain/lib.html.jinja
sphinx_bib_domain/_templates/bib_domain/lib.rst.jinja
sphinx_bib_domain/builder/__init__.py
sphinx_bib_domain/builder/bib_html_builder.py
sphinx_bib_domain/directives/__init__.py
sphinx_bib_domain/directives/bib_entry.py
sphinx_bib_domain/error/__init__.py
sphinx_bib_domain/indices/__init__.py
sphinx_bib_domain/indices/author.py
sphinx_bib_domain/indices/institution.py
sphinx_bib_domain/indices/journal.py
sphinx_bib_domain/indices/publisher.py
sphinx_bib_domain/indices/series.py
sphinx_bib_domain/indices/tag.py
sphinx_bib_domain/indices/year.py
sphinx_bib_domain/roles/__init__.py
sphinx_bib_domain/roles/_interface.py
sphinx_bib_domain/roles/author.py
sphinx_bib_domain/roles/doi.py
sphinx_bib_domain/roles/institution.py
sphinx_bib_domain/roles/journal.py
sphinx_bib_domain/roles/publisher.py
sphinx_bib_domain/roles/series.py
sphinx_bib_domain/roles/tag.py
sphinx_bib_domain/util/__init__.py
sphinx_bib_domain-0.2.0.dist-info/METADATA
sphinx_bib_domain-0.2.0.dist-info/WHEEL
sphinx_bib_domain-0.2.0.dist-info/entry_points.txt
sphinx_bib_domain-0.2.0.dist-info/licenses/LICENSE
sphinx_bib_domain-0.2.0.dist-info/RECORD
