Metadata-Version: 2.4
Name: sphinx_bib_domain
Version: 0.2.0
Project-URL: homepage, https://github.com/jgrey4296/sphinx_bib_domain
Project-URL: documentation, https://readthedocs.org/sphinx_bib_domain
Project-URL: repository, https://github.com/jgrey4296/sphinx_bib_domain
Project-URL: changelog, https://github.com//sphinx_bib_domain/blob/master/CHANGELOG.md
Author-email: John Grey <jgrey.n.plus.one+bibdomain@gmail.com>
License-File: LICENSE
Classifier: Programming Language :: Python
Requires-Python: >=3.12
Requires-Dist: bibtex-bibble>=0.3.1
Requires-Dist: docutils>=0.21.2
Requires-Dist: jgdv>=1.0.1
Requires-Dist: sphinx>=8.2.3
